README.rst
setup.py
confetti/__init__.py
confetti/__version__.py
confetti/config.py
confetti/exceptions.py
confetti/metadata.py
confetti/python3_compat.py
confetti/ref.py
confetti/utils.py
confetti.egg-info/PKG-INFO
confetti.egg-info/SOURCES.txt
confetti.egg-info/dependency_links.txt
confetti.egg-info/requires.txt
confetti.egg-info/top_level.txt