Metadata-Version: 1.1
Name: confetti
Version: 2.1.0
Summary: Generic configuration mechanism
Home-page: https://github.com/vmalloc/confetti
Author: Rotem Yaari
Author-email: vmalloc@gmail.com
License: BSD
Platform: UNKNOWN
Classifier: Development Status :: 4 - Beta
Classifier: Intended Audience :: Developers
Classifier: License :: OSI Approved :: BSD License
Classifier: Programming Language :: Python :: 2.7
